num_to_rus/__init__.py
num_to_rus/converter.py
num_to_rus/data_dicts.py
num_to_rus-1.1.0.dist-info/LICENSE
num_to_rus-1.1.0.dist-info/METADATA
num_to_rus-1.1.0.dist-info/WHEEL
num_to_rus-1.1.0.dist-info/top_level.txt
num_to_rus-1.1.0.dist-info/RECORD
