Metadata-Version: 2.1
Name: num_to_rus
Version: 1.1.0
Summary: Небольшая библиотека для перевода чисел в слова русского языка
Home-page: https://github.com/artemowkin/num_to_rus
Author: Artemowkin
Author-email: artyom.groshev2017@gmail.com
License: UNKNOWN
Platform: UNKNOWN
Classifier: Programming Language :: Python :: 3
Classifier: License :: OSI Approved :: GNU General Public License v3 (GPLv3)
Classifier: Operating System :: OS Independent
Requires-Python: >=3.7
License-File: LICENSE
